hibob_public_mcp/__init__.py
hibob_public_mcp/cli.py
hibob_public_mcp/mcp_server.py
hibob_public_mcp-0.4.0.dist-info/METADATA
hibob_public_mcp-0.4.0.dist-info/WHEEL
hibob_public_mcp-0.4.0.dist-info/entry_points.txt
hibob_public_mcp-0.4.0.dist-info/top_level.txt
hibob_public_mcp-0.4.0.dist-info/RECORD
