Metadata-Version: 2.4
Name: hibob-public-mcp
Version: 0.4.0
Summary: HiBob MCP server integration.
Author-email: Ori Danus <ori.danus@hibob.com>
Classifier: Programming Language :: Python :: 3
Classifier: License :: OSI Approved :: MIT License
Classifier: Operating System :: OS Independent
Requires-Python: >=3.8
Requires-Dist: fastmcp
Requires-Dist: requests
